Metadata-Version: 2.4
Name: juancobo6-marco-polo-timeseries
Version: 0.1.1
Summary: Python implementation of the game of marco polo with time dependencies.
Author-email: JuanCobo <juan.cobo@baobabsoluciones.es>
Requires-Python: >=3.12
Requires-Dist: pandas>=2.3.1
